{
  "type": "minecraft:block",
  "pools": [
    {
      "rolls": 1,
      "entries": [
        {
          "type": "minecraft:item",
          "functions": [
            {
              "function": "minecraft:copy_nbt",
              "source": "block_entity",
              "ops": [
                {
                  "source": "NetworkID",
                  "target": "BlockEntityTag.NetworkID",
                  "op": "replace"
                }
              ]
            }
          ],
          "name": "infernoreborn:essence_net_core"
        }
      ],
      "conditions": [
        {
          "condition": "minecraft:survives_explosion"
        }
      ]
    }
  ]
}